proxar/__init__.py
proxar/config.py
proxar/errors.py
proxar/handlers/fetch.py
proxar/handlers/storage.py
proxar/sources/free_proxy_list.py
proxar/sources/geonode.py
proxar/sources/open_proxy_list.py
proxar/sources/proxy_list.py
proxar/sources/proxyscrape.py
proxar-0.7.0.dist-info/METADATA
proxar-0.7.0.dist-info/WHEEL
proxar-0.7.0.dist-info/licenses/LICENSE
proxar-0.7.0.dist-info/RECORD
