Metadata-Version: 2.4
Name: proxar
Version: 0.7.0
Summary: A Python client for fetching public proxies from multiple sources.
Project-URL: Homepage, https://github.com/filming/proxar
Project-URL: Repository, https://github.com/filming/proxar
Project-URL: Issues, https://github.com/filming/proxar/issues
Project-URL: Changelog, https://github.com/filming/proxar/blob/master/CHANGELOG.md
Author: Filming
License: MIT License
License-File: LICENSE
Keywords: asyncio,proxies,proxy,python,python3,web-scraping
Classifier: Development Status :: 3 - Alpha
Classifier: Intended Audience :: Developers
Classifier: License :: OSI Approved :: MIT License
Classifier: Programming Language :: Python :: 3
Classifier: Programming Language :: Python :: 3.10
Classifier: Programming Language :: Python :: 3.11
Classifier: Programming Language :: Python :: 3.12
Classifier: Programming Language :: Python :: 3.13
Requires-Python: >=3.10
Requires-Dist: aiofiles>=24.1.0
Requires-Dist: aiohttp>=3.12.13
Requires-Dist: beautifulsoup4>=4.13.4
Requires-Dist: lxml>=6.0.0
Requires-Dist: platformdirs>=4.3.8
Requires-Dist: types-aiofiles>=24.1.0.20250606
